sigoptlite/__init__.py
sigoptlite/best_assignments.py
sigoptlite/broker.py
sigoptlite/builders.py
sigoptlite/driver.py
sigoptlite/models.py
sigoptlite/sources.py
sigoptlite/validators.py
sigoptlite-0.1.2.dist-info/LICENSE
sigoptlite-0.1.2.dist-info/METADATA
sigoptlite-0.1.2.dist-info/WHEEL
sigoptlite-0.1.2.dist-info/top_level.txt
sigoptlite-0.1.2.dist-info/RECORD
